{"cameraMode":{"drawMode":0,"name":"Shaded","section":"Shading Mode"},"sceneLighting":false,"audioPlay":false,"sceneViewState":{"m_AlwaysRefresh":false,"showFog":true,"showSkybox":false,"showFlares":true,"showImageEffects":true,"showParticleSystems":true,"showVisualEffectGraphs":true,"m_FxEnabled":true},"in2DMode":false,"pivot":{"x":-0.4541967809200287,"y":0.14262144267559052,"z":-0.8329168558120728},"rotation":{"x":-0.12054038047790528,"y":0.8652178049087524,"z":-0.24954354763031007,"w":-0.4179120361804962},"size":2.4655847549438478,"orthographic":false}